devpi_auth_gitlab/__init__.py
devpi_auth_gitlab/main.py
devpi_auth_gitlab-1.7.dist-info/METADATA
devpi_auth_gitlab-1.7.dist-info/WHEEL
devpi_auth_gitlab-1.7.dist-info/entry_points.txt
devpi_auth_gitlab-1.7.dist-info/top_level.txt
devpi_auth_gitlab-1.7.dist-info/RECORD
