Metadata-Version: 2.1
Name: devpi-auth-gitlab
Version: 1.7
Summary: An authentication plugin for use with gitlab-ci, utilising the build in registry token authentication scheme
Home-page: https://gitlab.com/andrewleech/devpi-gitlab-auth
Author: Andrew Leech
Author-email: andrew@alelec.net
License: UNKNOWN
Keywords: devpi plugin
Platform: UNKNOWN
Requires-Dist: requests
Requires-Dist: devpi-server (>=2.0.0)
